sotrans_fastapi_keycloak/__init__.py
sotrans_fastapi_keycloak/_roles.py
sotrans_fastapi_keycloak/_uuid.py
sotrans_fastapi_keycloak/api.py
sotrans_fastapi_keycloak/exceptions.py
sotrans_fastapi_keycloak/model.py
sotrans_fastapi_keycloak/role.py
sotrans_fastapi_keycloak-1.2.1.dist-info/LICENSE
sotrans_fastapi_keycloak-1.2.1.dist-info/METADATA
sotrans_fastapi_keycloak-1.2.1.dist-info/WHEEL
sotrans_fastapi_keycloak-1.2.1.dist-info/top_level.txt
sotrans_fastapi_keycloak-1.2.1.dist-info/RECORD
