Metadata-Version: 2.1
Name: sotrans-fastapi-keycloak
Version: 1.2.1
Author-email: Jonas Scholl <jonas@code-specialist.com>, Yannic Schröer <yannic@code-specialist.com>
Maintainer-email: Jonas Scholl <jonas@code-specialist.com>, Yannic Schröer <yannic@code-specialist.com>
Keywords: Keycloak,FastAPI,Authentication,Authorization
Classifier: Development Status :: 3 - Alpha
Classifier: Intended Audience :: Developers
Classifier: Topic :: Internet :: WWW/HTTP :: Session
Classifier: Topic :: Internet :: WWW/HTTP :: WSGI
Classifier: Topic :: Software Development :: Libraries :: Application Frameworks
Classifier: Topic :: Software Development :: Libraries :: Python Modules
Classifier: Framework :: FastAPI
Classifier: License :: OSI Approved :: Apache Software License
Classifier: Programming Language :: Python :: 3.10
Requires-Python: >=3.10
License-File: LICENSE
Requires-Dist: certifi ==2023.7.22
Requires-Dist: charset-normalizer ==3.2.0
Requires-Dist: fastapi ==0.100.1
Requires-Dist: idna ==3.4
Requires-Dist: python-jose ==3.3.0
Requires-Dist: pydantic <3.0,>=2.3.0
Requires-Dist: requests ==2.31.0
Requires-Dist: sniffio ==1.3.0
Requires-Dist: starlette ==0.27.0
Requires-Dist: typing-extensions ==4.7.1
Requires-Dist: urllib3 ==2.0.4
